encfix.py
encfix-0.2.dist-info/LICENSE
encfix-0.2.dist-info/METADATA
encfix-0.2.dist-info/WHEEL
encfix-0.2.dist-info/entry_points.txt
encfix-0.2.dist-info/top_level.txt
encfix-0.2.dist-info/zip-safe
encfix-0.2.dist-info/RECORD
