Metadata-Version: 2.1
Name: encfix
Version: 0.2
Summary: Guess and fix character encodings of garbled filenames
Home-page: https://github.com/Arnie97/encfix
Author: Arnie97
Author-email: arnie97@gmail.com
License: GPLv3+
Platform: UNKNOWN
Classifier: Development Status :: 4 - Beta
Classifier: Environment :: Console
Classifier: Intended Audience :: End Users/Desktop
Classifier: License :: OSI Approved :: GNU General Public License v3 or later (GPLv3+)
Classifier: Programming Language :: Python :: 3
Classifier: Programming Language :: Python :: 3 :: Only
Classifier: Topic :: Utilities
Requires-Python: >=3.0
Requires-Dist: chardet
